<?xml version="1.0" encoding="UTF-8"?>
<metadata>
  <identifier>BNA-DIG-ESSONEWS-1984-01</identifier>
  <mediatype>texts</mediatype>
  <collection>opensource</collection>
  <creator>Lago Oil and Transport Co. Ltd.</creator>
  <date>1984-01</date>
  <description>&lt;div&gt;Aruba Esso News (January 1984)&lt;/div&gt;&lt;div&gt;A monthly publication by Lago Oil &amp; Transport Co. Ltd. (San Nicolas, Aruba) in English and Papiamento.&lt;br /&gt;&lt;/div&gt;&lt;div&gt;&lt;br /&gt;&lt;/div&gt;&lt;div&gt;Digitized and made available online by &lt;a href="http://www.archive.org/details/bibliotecanacionalaruba" rel="nofollow"&gt;Biblioteca Nacional Aruba&lt;/a&gt;&lt;/div&gt;</description>
  <language>eng</language>
  <scanner>Biblioteca Nacional Aruba</scanner>
  <subject>company publications</subject>
  <title>Aruba Esso News (January 1984)</title>
  <language>Papiamento</language>
  <subject>Aruba</subject>
  <subject>San Nicolas</subject>
  <subject>Lago Oil &amp; Transport Co. Ltd.</subject>
  <subject>oil industry</subject>
  <subject>refineries</subject>
  <subject>community</subject>
  <subject>events</subject>
  <subject>people</subject>
  <subject>sports</subject>
  <subject>Standard Oil of New Jersey</subject>
</metadata>
